{"id": "GAO-16-141", "inputs": [{"text": "in recent years , there has been an increased focus on extending learning time as a key strategy for turning around the nation's low - performing schools .", "tokens": ["in", "recent", "years", ",", "there", "has", "been", "an", "increased", "focus", "on", "extending", "learning", "time", "as", "a", "key", "strategy", "for", "turning", "around", "the", "nation", "'s", "low", "-", "performing", "schools", "."], "sentence_id": 1, "word_count": 29}, {"text": "for example , in 2010 , the department of education ( education ) made significant changes to the requirements in its school improvement grants program ( sig program ) \u2014 funded at about $506 million in fiscal year 2015 \u2014 which required certain school districts to extend students' learning time as a key strategy for improving the lowest - performing schools .", "tokens": ["for", "example", ",", "in", "2010", ",", "the", "department", "of", "education", "(", "education", ")", "made", "significant", "changes", "to", "the", "requirements", "in", "its", "school", "improvement", "grants", "program", "(", "sig", "program", ")", "\u2014", "funded", "at", "about", "$", "506", "million", "in", "fiscal", "year", "2015", "\u2014", "which", "required", "certain", "school", "districts", "to", "extend", "students", "'", "learning", "time", "as", "a", "key", "strategy", "for", "improving", "the", "lowest", "-", "performing", "schools", "."], "sentence_id": 2, "word_count": 64}, {"text": "in addition to changes in the sig program , education in 2012 began to allow states to request waivers to permit the use of funds from its $1.2 billion 21st century community learning centers program ( 21st century ) to conduct authorized program activities during the school day , week , or year in schools that have implemented extended learning time .", "tokens": ["in", "addition", "to", "changes", "in", "the", "sig", "program", ",", "education", "in", "2012", "began", "to", "allow", "states", "to", "request", "waivers", "to", "permit", "the", "use", "of", "funds", "from", "its", "$", "1.2", "billion", "21st", "century", "community", "learning", "centers", "program", "(", "21st", "century", ")", "to", "conduct", "authorized", "program", "activities", "during", "the", "school", "day", ",", "week", ",", "or", "year", "in", "schools", "that", "have", "implemented", "extended", "learning", "time", "."], "sentence_id": 3, "word_count": 63}, {"text": "extended learning time \u2014 sometimes referred to as increased learning time or expanded learning time \u2014 aims to improve student achievement in a variety of ways including lengthening the school day , week , or year , providing before - and after - school activities , and providing summer programs .", "tokens": ["extended", "learning", "time", "\u2014", "sometimes", "referred", "to", "as", "increased", "learning", "time", "or", "expanded", "learning", "time", "\u2014", "aims", "to", "improve", "student", "achievement", "in", "a", "variety", "of", "ways", "including", "lengthening", "the", "school", "day", ",", "week", ",", "or", "year", ",", "providing", "before", "-", "and", "after", "-", "school", "activities", ",", "and", "providing", "summer", "programs", "."], "sentence_id": 4, "word_count": 51}, {"text": "all states require a minimum amount of instructional time in a school year , according to a 2015 education commission of the states study .", "tokens": ["all", "states", "require", "a", "minimum", "amount", "of", "instructional", "time", "in", "a", "school", "year", ",", "according", "to", "a", "2015", "education", "commission", "of", "the", "states", "study", "."], "sentence_id": 5, "word_count": 25}, {"text": "however , the study found that states vary in how they define that time in terms of days and hours and the requirements school districts must meet .", "tokens": ["however", ",", "the", "study", "found", "that", "states", "vary", "in", "how", "they", "define", "that", "time", "in", "terms", "of", "days", "and", "hours", "and", "the", "requirements", "school", "districts", "must", "meet", "."], "sentence_id": 6, "word_count": 28}, {"text": "further , school districts often vary in how much time they have in a school year beyond their state - mandated requirements .", "tokens": ["further", ",", "school", "districts", "often", "vary", "in", "how", "much", "time", "they", "have", "in", "a", "school", "year", "beyond", "their", "state", "-", "mandated", "requirements", "."], "sentence_id": 7, "word_count": 23}, {"text": "consequently , it can be difficult to determine what constitutes an extended school day , week , or year .", "tokens": ["consequently", ",", "it", "can", "be", "difficult", "to", "determine", "what", "constitutes", "an", "extended", "school", "day", ",", "week", ",", "or", "year", "."], "sentence_id": 8, "word_count": 20}, {"text": "a statement accompanying the consolidated and further continuing appropriations act of 2015 included a provision for us to review these issues .", "tokens": ["a", "statement", "accompanying", "the", "consolidated", "and", "further", "continuing", "appropriations", "act", "of", "2015", "included", "a", "provision", "for", "us", "to", "review", "these", "issues", "."], "sentence_id": 9, "word_count": 22}, {"text": "in this report , we examined what is known about 1 ) various education programs that can be used to support extended learning time for k - 12 students and 2 ) learning time in public schools nationwide .", "tokens": ["in", "this", "report", ",", "we", "examined", "what", "is", "known", "about", "1", ")", "various", "education", "programs", "that", "can", "be", "used", "to", "support", "extended", "learning", "time", "for", "k", "-", "12", "students", "and", "2", ")", "learning", "time", "in", "public", "schools", "nationwide", "."], "sentence_id": 10, "word_count": 39}, {"text": "see 160 cong .", "tokens": ["see", "160", "cong", "."], "sentence_id": 11, "word_count": 4}, {"text": "rec .", "tokens": ["rec", "."], "sentence_id": 12, "word_count": 2}, {"text": "h9307 , h9841 ( daily ed .", "tokens": ["h9307", ",", "h9841", "(", "daily", "ed", "."], "sentence_id": 13, "word_count": 7}, {"text": "dec. 11 , 2014 ) ( explanatory statement ) , accompanying pub .", "tokens": ["dec.", "11", ",", "2014", ")", "(", "explanatory", "statement", ")", ",", "accompanying", "pub", "."], "sentence_id": 14, "word_count": 13}, {"text": "l. no .", "tokens": ["l.", "no", "."], "sentence_id": 15, "word_count": 3}, {"text": "113-235 , 128 stat .", "tokens": ["113-235", ",", "128", "stat", "."], "sentence_id": 16, "word_count": 5}, {"text": "2130 ( 2014 ) .", "tokens": ["2130", "(", "2014", ")", "."], "sentence_id": 17, "word_count": 5}, {"text": "focused on programs that allow or require school districts to use program funds to lengthen the school day , week , or year for all students in a school .", "tokens": ["focused", "on", "programs", "that", "allow", "or", "require", "school", "districts", "to", "use", "program", "funds", "to", "lengthen", "the", "school", "day", ",", "week", ",", "or", "year", "for", "all", "students", "in", "a", "school", "."], "sentence_id": 18, "word_count": 30}, {"text": "activities that take place beyond the regular school day , such as after - school activities and programs or summer school programs , are outside the scope of this review .", "tokens": ["activities", "that", "take", "place", "beyond", "the", "regular", "school", "day", ",", "such", "as", "after", "-", "school", "activities", "and", "programs", "or", "summer", "school", "programs", ",", "are", "outside", "the", "scope", "of", "this", "review", "."], "sentence_id": 19, "word_count": 31}, {"text": "we also reviewed relevant federal laws , regulations , guidance , and program - specific information , such as program performance reports .", "tokens": ["we", "also", "reviewed", "relevant", "federal", "laws", ",", "regulations", ",", "guidance", ",", "and", "program", "-", "specific", "information", ",", "such", "as", "program", "performance", "reports", "."], "sentence_id": 20, "word_count": 23}, {"text": "we analyzed sig program data for school years 2010-2011 through 2014-2015 .", "tokens": ["we", "analyzed", "sig", "program", "data", "for", "school", "years", "2010-2011", "through", "2014-2015", "."], "sentence_id": 21, "word_count": 12}, {"text": "we assessed data reliability by reviewing existing information about the data system .", "tokens": ["we", "assessed", "data", "reliability", "by", "reviewing", "existing", "information", "about", "the", "data", "system", "."], "sentence_id": 22, "word_count": 13}, {"text": "we determined that the data were sufficiently reliable for the purposes of this report .", "tokens": ["we", "determined", "that", "the", "data", "were", "sufficiently", "reliable", "for", "the", "purposes", "of", "this", "report", "."], "sentence_id": 23, "word_count": 15}, {"text": "we also interviewed education officials and other key stakeholders to clarify which federal program funds schools may be using for this purpose .", "tokens": ["we", "also", "interviewed", "education", "officials", "and", "other", "key", "stakeholders", "to", "clarify", "which", "federal", "program", "funds", "schools", "may", "be", "using", "for", "this", "purpose", "."], "sentence_id": 24, "word_count": 23}, {"text": "the key stakeholders included officials from organizations that provide and / or are familiar with extended learning time as well as from organizations that represent state educational agencies , school districts , and teachers .", "tokens": ["the", "key", "stakeholders", "included", "officials", "from", "organizations", "that", "provide", "and", "/", "or", "are", "familiar", "with", "extended", "learning", "time", "as", "well", "as", "from", "organizations", "that", "represent", "state", "educational", "agencies", ",", "school", "districts", ",", "and", "teachers", "."], "sentence_id": 25, "word_count": 35}, {"text": "we identified organizations based on a review of selected literature and discussions with education officials .", "tokens": ["we", "identified", "organizations", "based", "on", "a", "review", "of", "selected", "literature", "and", "discussions", "with", "education", "officials", "."], "sentence_id": 26, "word_count": 16}, {"text": "to determine what is known about learning time in public schools nationwide , we analyzed national data from education's schools and staffing survey ( sass ) for school year 2011-2012 , the most recent year for which data were available .", "tokens": ["to", "determine", "what", "is", "known", "about", "learning", "time", "in", "public", "schools", "nationwide", ",", "we", "analyzed", "national", "data", "from", "education", "'s", "schools", "and", "staffing", "survey", "(", "sass", ")", "for", "school", "year", "2011-2012", ",", "the", "most", "recent", "year", "for", "which", "data", "were", "available", "."], "sentence_id": 27, "word_count": 42}, {"text": "sass contains data from a generalizable sample of k - 12 public elementary and secondary schools nationwide .", "tokens": ["sass", "contains", "data", "from", "a", "generalizable", "sample", "of", "k", "-", "12", "public", "elementary", "and", "secondary", "schools", "nationwide", "."], "sentence_id": 28, "word_count": 18}, {"text": "we used sass data to estimate the distribution of instructional time by hours per day and days per year .", "tokens": ["we", "used", "sass", "data", "to", "estimate", "the", "distribution", "of", "instructional", "time", "by", "hours", "per", "day", "and", "days", "per", "year", "."], "sentence_id": 29, "word_count": 20}, {"text": "to identify schools with the most learning time , we created a measure of the number of hours each school provides annually .", "tokens": ["to", "identify", "schools", "with", "the", "most", "learning", "time", ",", "we", "created", "a", "measure", "of", "the", "number", "of", "hours", "each", "school", "provides", "annually", "."], "sentence_id": 30, "word_count": 23}, {"text": "this measure of annual school time was calculated by multiplying the number of hours of instruction that students receive per day by the number of days the school operates during the school year .", "tokens": ["this", "measure", "of", "annual", "school", "time", "was", "calculated", "by", "multiplying", "the", "number", "of", "hours", "of", "instruction", "that", "students", "receive", "per", "day", "by", "the", "number", "of", "days", "the", "school", "operates", "during", "the", "school", "year", "."], "sentence_id": 31, "word_count": 34}, {"text": "to describe the characteristics of schools with the most learning time , we analyzed schools with the most school hours annually , which we defined as the top 10 percent of schools , and compared them with the remaining 90 percent of schools .", "tokens": ["to", "describe", "the", "characteristics", "of", "schools", "with", "the", "most", "learning", "time", ",", "we", "analyzed", "schools", "with", "the", "most", "school", "hours", "annually", ",", "which", "we", "defined", "as", "the", "top", "10", "percent", "of", "schools", ",", "and", "compared", "them", "with", "the", "remaining", "90", "percent", "of", "schools", "."], "sentence_id": 32, "word_count": 44}, {"text": "for this analysis we looked at selected school characteristics from the sass dataset , including the length of the school day ; number of days in the school year ; school level and type ( e.g. , traditional public and charter schools ) ; location ( e.g. , census region and urban vs. rural locations ) ; and student demographics , such as race , ethnicity , and socioeconomic status .", "tokens": ["for", "this", "analysis", "we", "looked", "at", "selected", "school", "characteristics", "from", "the", "sass", "dataset", ",", "including", "the", "length", "of", "the", "school", "day", ";", "number", "of", "days", "in", "the", "school", "year", ";", "school", "level", "and", "type", "(", "e.g", ".", ",", "traditional", "public", "and", "charter", "schools", ")", ";", "location", "(", "e.g", ".", ",", "census", "region", "and", "urban", "vs.", "rural", "locations", ")", ";", "and", "student", "demographics", ",", "such", "as", "race", ",", "ethnicity", ",", "and", "socioeconomic", "status", "."], "sentence_id": 33, "word_count": 73}, {"text": "we assessed data reliability by reviewing existing information about the data system .", "tokens": ["we", "assessed", "data", "reliability", "by", "reviewing", "existing", "information", "about", "the", "data", "system", "."], "sentence_id": 34, "word_count": 13}, {"text": "we determined that the data were sufficiently reliable for the purposes of this report .", "tokens": ["we", "determined", "that", "the", "data", "were", "sufficiently", "reliable", "for", "the", "purposes", "of", "this", "report", "."], "sentence_id": 35, "word_count": 15}, {"text": "for both research objectives , we reviewed selected reports on extended learning time , including how schools fund extended learning time initiatives and how schools use the additional time in the school day .", "tokens": ["for", "both", "research", "objectives", ",", "we", "reviewed", "selected", "reports", "on", "extended", "learning", "time", ",", "including", "how", "schools", "fund", "extended", "learning", "time", "initiatives", "and", "how", "schools", "use", "the", "additional", "time", "in", "the", "school", "day", "."], "sentence_id": 36, "word_count": 34}, {"text": "we conducted this performance audit from june 2015 to november 2015 in accordance with generally accepted government auditing standards .", "tokens": ["we", "conducted", "this", "performance", "audit", "from", "june", "2015", "to", "november", "2015", "in", "accordance", "with", "generally", "accepted", "government", "auditing", "standards", "."], "sentence_id": 37, "word_count": 20}, {"text": "those standards require that we plan and perform the audit to obtain sufficient , appropriate evidence to provide a reasonable basis for our findings and conclusions based on our audit objectives .", "tokens": ["those", "standards", "require", "that", "we", "plan", "and", "perform", "the", "audit", "to", "obtain", "sufficient", ",", "appropriate", "evidence", "to", "provide", "a", "reasonable", "basis", "for", "our", "findings", "and", "conclusions", "based", "on", "our", "audit", "objectives", "."], "sentence_id": 38, "word_count": 32}, {"text": "we believe that the evidence obtained provides a reasonable basis for our findings and conclusions based on our audit objectives .", "tokens": ["we", "believe", "that", "the", "evidence", "obtained", "provides", "a", "reasonable", "basis", "for", "our", "findings", "and", "conclusions", "based", "on", "our", "audit", "objectives", "."], "sentence_id": 39, "word_count": 21}, {"text": "the school improvement grants ( sig ) program was created in 2002 and funds reforms in the country's lowest - performing schools with the goal of improving student outcomes , such as their standardized test scores and graduation rates .", "tokens": ["the", "school", "improvement", "grants", "(", "sig", ")", "program", "was", "created", "in", "2002", "and", "funds", "reforms", "in", "the", "country", "'s", "lowest", "-", "performing", "schools", "with", "the", "goal", "of", "improving", "student", "outcomes", ",", "such", "as", "their", "standardized", "test", "scores", "and", "graduation", "rates", "."], "sentence_id": 40, "word_count": 41}, {"text": "congress greatly increased sig program funding , from $125 million available in fiscal year 2007 \u2014 the first year the program was funded \u2014 to $3.5 billion in fiscal year 2009 , although funding for the last two fiscal years has been $506 million a year .", "tokens": ["congress", "greatly", "increased", "sig", "program", "funding", ",", "from", "$", "125", "million", "available", "in", "fiscal", "year", "2007", "\u2014", "the", "first", "year", "the", "program", "was", "funded", "\u2014", "to", "$", "3.5", "billion", "in", "fiscal", "year", "2009", ",", "although", "funding", "for", "the", "last", "two", "fiscal", "years", "has", "been", "$", "506", "million", "a", "year", "."], "sentence_id": 41, "word_count": 50}, {"text": "before awarding formula grants to states , education reviews each state's application and approves the state's proposed process for competitively awarding sig subgrants to eligible entities , including school districts .", "tokens": ["before", "awarding", "formula", "grants", "to", "states", ",", "education", "reviews", "each", "state", "'s", "application", "and", "approves", "the", "state", "'s", "proposed", "process", "for", "competitively", "awarding", "sig", "subgrants", "to", "eligible", "entities", ",", "including", "school", "districts", "."], "sentence_id": 42, "word_count": 33}, {"text": "as a part of its application , each state is required to identify and prioritize eligible schools and ensure that school districts with the persistently lowest - achieving schools receive sig funding .", "tokens": ["as", "a", "part", "of", "its", "application", ",", "each", "state", "is", "required", "to", "identify", "and", "prioritize", "eligible", "schools", "and", "ensure", "that", "school", "districts", "with", "the", "persistently", "lowest", "-", "achieving", "schools", "receive", "sig", "funding", "."], "sentence_id": 43, "word_count": 33}, {"text": "school districts must then apply to states to implement one of seven intervention models in each sig school , each with specific requirements for reform interventions , during a grant period between 3 and 5 years .", "tokens": ["school", "districts", "must", "then", "apply", "to", "states", "to", "implement", "one", "of", "seven", "intervention", "models", "in", "each", "sig", "school", ",", "each", "with", "specific", "requirements", "for", "reform", "interventions", ",", "during", "a", "grant", "period", "between", "3", "and", "5", "years", "."], "sentence_id": 44, "word_count": 37}, {"text": "two of these intervention models , which are being implemented in the large majority of current sig schools , require schools to extend learning time as part of the required whole - school reform strategies .", "tokens": ["two", "of", "these", "intervention", "models", ",", "which", "are", "being", "implemented", "in", "the", "large", "majority", "of", "current", "sig", "schools", ",", "require", "schools", "to", "extend", "learning", "time", "as", "part", "of", "the", "required", "whole", "-", "school", "reform", "strategies", "."], "sentence_id": 45, "word_count": 36}, {"text": "sig requirements define increased learning time as using a longer school day , week , or year to significantly increase the total number of school hours .", "tokens": ["sig", "requirements", "define", "increased", "learning", "time", "as", "using", "a", "longer", "school", "day", ",", "week", ",", "or", "year", "to", "significantly", "increase", "the", "total", "number", "of", "school", "hours", "."], "sentence_id": 46, "word_count": 27}, {"text": "this additional time is to be used for ( 1 ) instruction in academic subjects , including english , reading or language arts , mathematics , science , foreign languages , civics and government , economics , arts , history , and geography ; ( 2 ) instruction in other subjects and provision of enrichment activities that contribute to a well - rounded education , such as physical education , service learning , and experiential and work - based learning opportunities ; and ( 3 ) teachers to collaborate , plan , and engage in professional development within and across grades and subjects .", "tokens": ["this", "additional", "time", "is", "to", "be", "used", "for", "(", "1", ")", "instruction", "in", "academic", "subjects", ",", "including", "english", ",", "reading", "or", "language", "arts", ",", "mathematics", ",", "science", ",", "foreign", "languages", ",", "civics", "and", "government", ",", "economics", ",", "arts", ",", "history", ",", "and", "geography", ";", "(", "2", ")", "instruction", "in", "other", "subjects", "and", "provision", "of", "enrichment", "activities", "that", "contribute", "to", "a", "well", "-", "rounded", "education", ",", "such", "as", "physical", "education", ",", "service", "learning", ",", "and", "experiential", "and", "work", "-", "based", "learning", "opportunities", ";", "and", "(", "3", ")", "teachers", "to", "collaborate", ",", "plan", ",", "and", "engage", "in", "professional", "development", "within", "and", "across", "grades", "and", "subjects", "."], "sentence_id": 47, "word_count": 104}, {"text": "the 21st century community learning centers program ( 21st century ) is meant to support local communities in establishing or expanding community learning centers that provide opportunities for academic enrichment during non - school hours , such as before - and after - school and summer school programs , and related services to students' families .", "tokens": ["the", "21st", "century", "community", "learning", "centers", "program", "(", "21st", "century", ")", "is", "meant", "to", "support", "local", "communities", "in", "establishing", "or", "expanding", "community", "learning", "centers", "that", "provide", "opportunities", "for", "academic", "enrichment", "during", "non", "-", "school", "hours", ",", "such", "as", "before", "-", "and", "after", "-", "school", "and", "summer", "school", "programs", ",", "and", "related", "services", "to", "students", "'", "families", "."], "sentence_id": 48, "word_count": 57}, {"text": "the program provides formula grants to state educational agencies ( sea ) , which subsequently offer competitive subgrants to eligible entities , including school districts , community - based organizations , and other public or private entities .", "tokens": ["the", "program", "provides", "formula", "grants", "to", "state", "educational", "agencies", "(", "sea", ")", ",", "which", "subsequently", "offer", "competitive", "subgrants", "to", "eligible", "entities", ",", "including", "school", "districts", ",", "community", "-", "based", "organizations", ",", "and", "other", "public", "or", "private", "entities", "."], "sentence_id": 49, "word_count": 38}, {"text": "seas must provide an assurance in their applications for 21st century grants that they will make awards only to eligible entities that propose to serve students who primarily attend schools eligible to operate a schoolwide program under title i of the elementary and secondary education act of 1965 , as amended ( esea ) , which are schools with at least 40 percent of students from low - income families .", "tokens": ["seas", "must", "provide", "an", "assurance", "in", "their", "applications", "for", "21st", "century", "grants", "that", "they", "will", "make", "awards", "only", "to", "eligible", "entities", "that", "propose", "to", "serve", "students", "who", "primarily", "attend", "schools", "eligible", "to", "operate", "a", "schoolwide", "program", "under", "title", "i", "of", "the", "elementary", "and", "secondary", "education", "act", "of", "1965", ",", "as", "amended", "(", "esea", ")", ",", "which", "are", "schools", "with", "at", "least", "40", "percent", "of", "students", "from", "low", "-", "income", "families", "."], "sentence_id": 50, "word_count": 71}, {"text": "in addition to activities designed to help students meet state and local academic achievement standards , program funds may be used to provide activities that complement and reinforce a student's regular school - day program , such as art and music education activities , recreational activities , telecommunications and technology education programs , expanded library hours , literacy programs , and drug and violence prevention activities .", "tokens": ["in", "addition", "to", "activities", "designed", "to", "help", "students", "meet", "state", "and", "local", "academic", "achievement", "standards", ",", "program", "funds", "may", "be", "used", "to", "provide", "activities", "that", "complement", "and", "reinforce", "a", "student", "'s", "regular", "school", "-", "day", "program", ",", "such", "as", "art", "and", "music", "education", "activities", ",", "recreational", "activities", ",", "telecommunications", "and", "technology", "education", "programs", ",", "expanded", "library", "hours", ",", "literacy", "programs", ",", "and", "drug", "and", "violence", "prevention", "activities", "."], "sentence_id": 51, "word_count": 68}, {"text": "in fiscal year 2012 , education began to invite seas to waive specific esea provisions , which require community learning centers to carry out their activities during non - school hours or periods when school is not in session .", "tokens": ["in", "fiscal", "year", "2012", ",", "education", "began", "to", "invite", "seas", "to", "waive", "specific", "esea", "provisions", ",", "which", "require", "community", "learning", "centers", "to", "carry", "out", "their", "activities", "during", "non", "-", "school", "hours", "or", "periods", "when", "school", "is", "not", "in", "session", "."], "sentence_id": 52, "word_count": 40}, {"text": "the waiver allows grantees to use 21st century program funds to conduct authorized activities during an extended school day , week , or year in schools that provide extended learning time for all students in the school .", "tokens": ["the", "waiver", "allows", "grantees", "to", "use", "21st", "century", "program", "funds", "to", "conduct", "authorized", "activities", "during", "an", "extended", "school", "day", ",", "week", ",", "or", "year", "in", "schools", "that", "provide", "extended", "learning", "time", "for", "all", "students", "in", "the", "school", "."], "sentence_id": 53, "word_count": 38}, {"text": "education's guidance for the 21st century program defines \u201cexpanded learning time\u201d as \u201cadditional instruction or educational programs for all students beyond the state - mandated requirements for the minimum number of hours in a school day , days in a school week , or days or weeks in a school year.\u201d according to education guidance , these activities can include supplemental academic enrichment activities that support a well - rounded education for students and increase collaboration and planning time for teachers , or for partnering with outside organizations , such as nonprofit organizations , that have demonstrated experience in improving student achievement .", "tokens": ["education", "'s", "guidance", "for", "the", "21st", "century", "program", "defines", "\u201c", "expanded", "learning", "time", "\u201d", "as", "\u201c", "additional", "instruction", "or", "educational", "programs", "for", "all", "students", "beyond", "the", "state", "-", "mandated", "requirements", "for", "the", "minimum", "number", "of", "hours", "in", "a", "school", "day", ",", "days", "in", "a", "school", "week", ",", "or", "days", "or", "weeks", "in", "a", "school", "year.", "\u201d", "according", "to", "education", "guidance", ",", "these", "activities", "can", "include", "supplemental", "academic", "enrichment", "activities", "that", "support", "a", "well", "-", "rounded", "education", "for", "students", "and", "increase", "collaboration", "and", "planning", "time", "for", "teachers", ",", "or", "for", "partnering", "with", "outside", "organizations", ",", "such", "as", "nonprofit", "organizations", ",", "that", "have", "demonstrated", "experience", "in", "improving", "student", "achievement", "."], "sentence_id": 54, "word_count": 108}, {"text": "the vast majority of funding for k - 12 public schools nationwide comes from state and local sources .", "tokens": ["the", "vast", "majority", "of", "funding", "for", "k", "-", "12", "public", "schools", "nationwide", "comes", "from", "state", "and", "local", "sources", "."], "sentence_id": 55, "word_count": 19}, {"text": "for example , in school year 2009-2010 , u.s. public schools received about 87 percent of their funding from state and local sources \u2014 43 percent from state sources and 44 percent from local sources .", "tokens": ["for", "example", ",", "in", "school", "year", "2009-2010", ",", "u.s.", "public", "schools", "received", "about", "87", "percent", "of", "their", "funding", "from", "state", "and", "local", "sources", "\u2014", "43", "percent", "from", "state", "sources", "and", "44", "percent", "from", "local", "sources", "."], "sentence_id": 56, "word_count": 36}, {"text": "federal funding has generally comprised about 9 percent of public schools' funding from school year 2002-2003 through 2008- 2009 .", "tokens": ["federal", "funding", "has", "generally", "comprised", "about", "9", "percent", "of", "public", "schools", "'", "funding", "from", "school", "year", "2002-2003", "through", "2008-", "2009", "."], "sentence_id": 57, "word_count": 21}, {"text": "in school year 2009-2010 , federal funding for public schools comprised about 13 percent , which was slightly higher than in previous years due in part to the american recovery and reinvestment act of 2009 .", "tokens": ["in", "school", "year", "2009-2010", ",", "federal", "funding", "for", "public", "schools", "comprised", "about", "13", "percent", ",", "which", "was", "slightly", "higher", "than", "in", "previous", "years", "due", "in", "part", "to", "the", "american", "recovery", "and", "reinvestment", "act", "of", "2009", "."], "sentence_id": 58, "word_count": 36}, {"text": "for public schools nationally , education's title i , part a of esea , is among the programs providing the largest amounts of federal funding .", "tokens": ["for", "public", "schools", "nationally", ",", "education", "'s", "title", "i", ",", "part", "a", "of", "esea", ",", "is", "among", "the", "programs", "providing", "the", "largest", "amounts", "of", "federal", "funding", "."], "sentence_id": 59, "word_count": 27}, {"text": "the school improvement grants ( sig ) program is the only program administered by education that provides funds specifically to establish extended learning time in a school , according to education officials .", "tokens": ["the", "school", "improvement", "grants", "(", "sig", ")", "program", "is", "the", "only", "program", "administered", "by", "education", "that", "provides", "funds", "specifically", "to", "establish", "extended", "learning", "time", "in", "a", "school", ",", "according", "to", "education", "officials", "."], "sentence_id": 60, "word_count": 33}, {"text": "between school year 2010-2011 , when changes were made to sig to require extended learning time in certain instances , and 2014-2015 , the last year sig data are available , nearly 1,800 schools or approximately 94 percent of sig schools had chosen either of two school improvement models that require extended learning time , out of the four available models ( see fig .", "tokens": ["between", "school", "year", "2010-2011", ",", "when", "changes", "were", "made", "to", "sig", "to", "require", "extended", "learning", "time", "in", "certain", "instances", ",", "and", "2014-2015", ",", "the", "last", "year", "sig", "data", "are", "available", ",", "nearly", "1,800", "schools", "or", "approximately", "94", "percent", "of", "sig", "schools", "had", "chosen", "either", "of", "two", "school", "improvement", "models", "that", "require", "extended", "learning", "time", ",", "out", "of", "the", "four", "available", "models", "(", "see", "fig", "."], "sentence_id": 61, "word_count": 65}, {"text": "1 ) .", "tokens": ["1", ")", "."], "sentence_id": 62, "word_count": 3}, {"text": "the schools implementing either of those two models had to extend learning time alongside other key reforms such as developing new teacher and principal evaluation systems .", "tokens": ["the", "schools", "implementing", "either", "of", "those", "two", "models", "had", "to", "extend", "learning", "time", "alongside", "other", "key", "reforms", "such", "as", "developing", "new", "teacher", "and", "principal", "evaluation", "systems", "."], "sentence_id": 63, "word_count": 27}, {"text": "however , these 1,800 schools represent a small fraction of the nearly 90,000 k - 12 public schools nationwide .", "tokens": ["however", ",", "these", "1,800", "schools", "represent", "a", "small", "fraction", "of", "the", "nearly", "90,000", "k", "-", "12", "public", "schools", "nationwide", "."], "sentence_id": 64, "word_count": 20}, {"text": "further , among the lowest - performing u.s. public schools , less than 7.5 percent are receiving sig funds , according to a 2012 institute of education sciences study .", "tokens": ["further", ",", "among", "the", "lowest", "-", "performing", "u.s.", "public", "schools", ",", "less", "than", "7.5", "percent", "are", "receiving", "sig", "funds", ",", "according", "to", "a", "2012", "institute", "of", "education", "sciences", "study", "."], "sentence_id": 65, "word_count": 30}, {"text": "although only about 1,800 schools have received assistance through sig grants , this assistance can be vital to a school in helping to implement key reforms such as extended learning time .", "tokens": ["although", "only", "about", "1,800", "schools", "have", "received", "assistance", "through", "sig", "grants", ",", "this", "assistance", "can", "be", "vital", "to", "a", "school", "in", "helping", "to", "implement", "key", "reforms", "such", "as", "extended", "learning", "time", "."], "sentence_id": 66, "word_count": 32}, {"text": "according to an education report on the 2012-2013 school year , the average 3-year grant was $2.6 million as of that year .", "tokens": ["according", "to", "an", "education", "report", "on", "the", "2012-2013", "school", "year", ",", "the", "average", "3-year", "grant", "was", "$", "2.6", "million", "as", "of", "that", "year", "."], "sentence_id": 67, "word_count": 24}, {"text": "education found that 68 percent of sig schools in school year 2010-2011 ( referred to as cohort 1 ) , 79 percent in school year 2011-2012 ( referred to as cohort 2 ) , and 83 percent of sig schools in school year 2012-2013 provided extended learning time .", "tokens": ["education", "found", "that", "68", "percent", "of", "sig", "schools", "in", "school", "year", "2010-2011", "(", "referred", "to", "as", "cohort", "1", ")", ",", "79", "percent", "in", "school", "year", "2011-2012", "(", "referred", "to", "as", "cohort", "2", ")", ",", "and", "83", "percent", "of", "sig", "schools", "in", "school", "year", "2012-2013", "provided", "extended", "learning", "time", "."], "sentence_id": 68, "word_count": 49}, {"text": "this is to be expected given that , as previously noted , most school districts have chosen a sig model that requires extended learning time .", "tokens": ["this", "is", "to", "be", "expected", "given", "that", ",", "as", "previously", "noted", ",", "most", "school", "districts", "have", "chosen", "a", "sig", "model", "that", "requires", "extended", "learning", "time", "."], "sentence_id": 69, "word_count": 26}, {"text": "on average , cohorts 1 and 2 had 76 and 96 more hours , respectively , than all public schools in school year 2011-2012 , according to education's analysis of sig grant reports .", "tokens": ["on", "average", ",", "cohorts", "1", "and", "2", "had", "76", "and", "96", "more", "hours", ",", "respectively", ",", "than", "all", "public", "schools", "in", "school", "year", "2011-2012", ",", "according", "to", "education", "'s", "analysis", "of", "sig", "grant", "reports", "."], "sentence_id": 70, "word_count": 35}, {"text": "additionally , a 2014 institute of education sciences study found that 71 percent of sig schools surveyed had extended learning time , while only 60 percent of non - grantee schools had taken steps to increase learning time .", "tokens": ["additionally", ",", "a", "2014", "institute", "of", "education", "sciences", "study", "found", "that", "71", "percent", "of", "sig", "schools", "surveyed", "had", "extended", "learning", "time", ",", "while", "only", "60", "percent", "of", "non", "-", "grantee", "schools", "had", "taken", "steps", "to", "increase", "learning", "time", "."], "sentence_id": 71, "word_count": 39}, {"text": "however , education officials also told us some schools increased learning time by very little , some by as little as 10 minutes a day .", "tokens": ["however", ",", "education", "officials", "also", "told", "us", "some", "schools", "increased", "learning", "time", "by", "very", "little", ",", "some", "by", "as", "little", "as", "10", "minutes", "a", "day", "."], "sentence_id": 72, "word_count": 26}, {"text": "in contrast to sig , where most sig schools are implementing extended learning time , as of july 2015 , education officials reported that only a fraction of the 21st century learning centers it funds \u2014 about 69 out of 10,000 nationwide \u2014 are supplementing local extended learning time initiatives by taking advantage of waivers of esea requirements that allow them to provide 21st century program activities and services during an extended school day .", "tokens": ["in", "contrast", "to", "sig", ",", "where", "most", "sig", "schools", "are", "implementing", "extended", "learning", "time", ",", "as", "of", "july", "2015", ",", "education", "officials", "reported", "that", "only", "a", "fraction", "of", "the", "21st", "century", "learning", "centers", "it", "funds", "\u2014", "about", "69", "out", "of", "10,000", "nationwide", "\u2014", "are", "supplementing", "local", "extended", "learning", "time", "initiatives", "by", "taking", "advantage", "of", "waivers", "of", "esea", "requirements", "that", "allow", "them", "to", "provide", "21st", "century", "program", "activities", "and", "services", "during", "an", "extended", "school", "day", "."], "sentence_id": 73, "word_count": 75}, {"text": "therefore , as required by statute , more than 99 percent of the centers continue to use these subgrants to serve students outside school hours , which according to education officials is typically in after - school programs where attendance is voluntary .", "tokens": ["therefore", ",", "as", "required", "by", "statute", ",", "more", "than", "99", "percent", "of", "the", "centers", "continue", "to", "use", "these", "subgrants", "to", "serve", "students", "outside", "school", "hours", ",", "which", "according", "to", "education", "officials", "is", "typically", "in", "after", "-", "school", "programs", "where", "attendance", "is", "voluntary", "."], "sentence_id": 74, "word_count": 43}, {"text": "the average subgrant per center was about $113,000 per school year .", "tokens": ["the", "average", "subgrant", "per", "center", "was", "about", "$", "113,000", "per", "school", "year", "."], "sentence_id": 75, "word_count": 13}, {"text": "regardless of whether subgrantees conduct activities during extended learning time or not , centers are to follow the same program rules about what types of activities can be funded .", "tokens": ["regardless", "of", "whether", "subgrantees", "conduct", "activities", "during", "extended", "learning", "time", "or", "not", ",", "centers", "are", "to", "follow", "the", "same", "program", "rules", "about", "what", "types", "of", "activities", "can", "be", "funded", "."], "sentence_id": 76, "word_count": 30}, {"text": "further , education said schools cannot use these funds to establish new programs to extend the school day .", "tokens": ["further", ",", "education", "said", "schools", "can", "not", "use", "these", "funds", "to", "establish", "new", "programs", "to", "extend", "the", "school", "day", "."], "sentence_id": 77, "word_count": 20}, {"text": "rather , they can be used only to supplement other programs and activities for all students in schools that had extended the normal school day , week , or year .", "tokens": ["rather", ",", "they", "can", "be", "used", "only", "to", "supplement", "other", "programs", "and", "activities", "for", "all", "students", "in", "schools", "that", "had", "extended", "the", "normal", "school", "day", ",", "week", ",", "or", "year", "."], "sentence_id": 78, "word_count": 31}, {"text": "education reported in its fiscal year 2015 budget justification that using 21st century funds in this way could improve 21st century program performance by minimizing or eliminating participation problems that many schools and other providers have experienced .", "tokens": ["education", "reported", "in", "its", "fiscal", "year", "2015", "budget", "justification", "that", "using", "21st", "century", "funds", "in", "this", "way", "could", "improve", "21st", "century", "program", "performance", "by", "minimizing", "or", "eliminating", "participation", "problems", "that", "many", "schools", "and", "other", "providers", "have", "experienced", "."], "sentence_id": 79, "word_count": 38}, {"text": "for example , education reported that nearly half of students attending 21st century activities attended for fewer than 30 days in school year 2012-2013 .", "tokens": ["for", "example", ",", "education", "reported", "that", "nearly", "half", "of", "students", "attending", "21st", "century", "activities", "attended", "for", "fewer", "than", "30", "days", "in", "school", "year", "2012-2013", "."], "sentence_id": 80, "word_count": 25}, {"text": "two extended learning time providers we interviewed said that changing from voluntary after - school activities to programs during the extended school day , which is generally mandatory for all students , helped reach underserved students who may not have chosen to attend if the activities were offered after school .", "tokens": ["two", "extended", "learning", "time", "providers", "we", "interviewed", "said", "that", "changing", "from", "voluntary", "after", "-", "school", "activities", "to", "programs", "during", "the", "extended", "school", "day", ",", "which", "is", "generally", "mandatory", "for", "all", "students", ",", "helped", "reach", "underserved", "students", "who", "may", "not", "have", "chosen", "to", "attend", "if", "the", "activities", "were", "offered", "after", "school", "."], "sentence_id": 81, "word_count": 51}, {"text": "since 2012 , 27 states have applied for esea waivers to allow 21st century grantees to conduct authorized activities during the school day to support extended learning time , and all were approved by education .", "tokens": ["since", "2012", ",", "27", "states", "have", "applied", "for", "esea", "waivers", "to", "allow", "21st", "century", "grantees", "to", "conduct", "authorized", "activities", "during", "the", "school", "day", "to", "support", "extended", "learning", "time", ",", "and", "all", "were", "approved", "by", "education", "."], "sentence_id": 82, "word_count": 36}, {"text": "however , as of july 2015 , only 11 of those states have schools that have implemented extended learning time programs .", "tokens": ["however", ",", "as", "of", "july", "2015", ",", "only", "11", "of", "those", "states", "have", "schools", "that", "have", "implemented", "extended", "learning", "time", "programs", "."], "sentence_id": 83, "word_count": 22}, {"text": "with regard to states' limited use of these waivers , education officials said that while the waivers have been available since mid - 2012 , extended learning time can be expensive to implement and it takes time for states to plan and collaborate with districts , schools , and community organizations .", "tokens": ["with", "regard", "to", "states", "'", "limited", "use", "of", "these", "waivers", ",", "education", "officials", "said", "that", "while", "the", "waivers", "have", "been", "available", "since", "mid", "-", "2012", ",", "extended", "learning", "time", "can", "be", "expensive", "to", "implement", "and", "it", "takes", "time", "for", "states", "to", "plan", "and", "collaborate", "with", "districts", ",", "schools", ",", "and", "community", "organizations", "."], "sentence_id": 84, "word_count": 53}, {"text": "additionally , education officials said states are not required to report the number of eligible entities using this waiver flexibility , so these numbers may be low .", "tokens": ["additionally", ",", "education", "officials", "said", "states", "are", "not", "required", "to", "report", "the", "number", "of", "eligible", "entities", "using", "this", "waiver", "flexibility", ",", "so", "these", "numbers", "may", "be", "low", "."], "sentence_id": 85, "word_count": 28}, {"text": "education is currently collecting data on conducting activities during the school day in schools with extended learning time for its 21st century programs for the first time , and officials told us they plan to report detailed figures in february 2016 on the number of hours and locations of all 21st century programs in schools with extended learning time .", "tokens": ["education", "is", "currently", "collecting", "data", "on", "conducting", "activities", "during", "the", "school", "day", "in", "schools", "with", "extended", "learning", "time", "for", "its", "21st", "century", "programs", "for", "the", "first", "time", ",", "and", "officials", "told", "us", "they", "plan", "to", "report", "detailed", "figures", "in", "february", "2016", "on", "the", "number", "of", "hours", "and", "locations", "of", "all", "21st", "century", "programs", "in", "schools", "with", "extended", "learning", "time", "."], "sentence_id": 86, "word_count": 60}, {"text": "education officials told us that most education funding streams are designed for use during the school day \u2013 regardless of the length of the school day or year \u2013 and as such , schools may use these funds during extended learning time , consistent with other program requirements .", "tokens": ["education", "officials", "told", "us", "that", "most", "education", "funding", "streams", "are", "designed", "for", "use", "during", "the", "school", "day", "\u2013", "regardless", "of", "the", "length", "of", "the", "school", "day", "or", "year", "\u2013", "and", "as", "such", ",", "schools", "may", "use", "these", "funds", "during", "extended", "learning", "time", ",", "consistent", "with", "other", "program", "requirements", "."], "sentence_id": 87, "word_count": 49}, {"text": "for example , schools may use funds from title i , part a of esea to serve all students in schools that operate a schoolwide program in which they serve a high - concentration of students from low - income families .", "tokens": ["for", "example", ",", "schools", "may", "use", "funds", "from", "title", "i", ",", "part", "a", "of", "esea", "to", "serve", "all", "students", "in", "schools", "that", "operate", "a", "schoolwide", "program", "in", "which", "they", "serve", "a", "high", "-", "concentration", "of", "students", "from", "low", "-", "income", "families", "."], "sentence_id": 88, "word_count": 42}, {"text": "education officials said that these funds could be used to supplement local funding to extend the school day for all students in those schools .", "tokens": ["education", "officials", "said", "that", "these", "funds", "could", "be", "used", "to", "supplement", "local", "funding", "to", "extend", "the", "school", "day", "for", "all", "students", "in", "those", "schools", "."], "sentence_id": 89, "word_count": 25}, {"text": "officials added that charter school grants may support eligible charter schools with or without extended learning time programs .", "tokens": ["officials", "added", "that", "charter", "school", "grants", "may", "support", "eligible", "charter", "schools", "with", "or", "without", "extended", "learning", "time", "programs", "."], "sentence_id": 90, "word_count": 19}, {"text": "charter school grants are primarily designed to assist in the planning , program design , and initial implementation of charter schools , either through the creation of new charter schools or the replication or the expansion of existing high - quality charter schools with demonstrated records of success .", "tokens": ["charter", "school", "grants", "are", "primarily", "designed", "to", "assist", "in", "the", "planning", ",", "program", "design", ",", "and", "initial", "implementation", "of", "charter", "schools", ",", "either", "through", "the", "creation", "of", "new", "charter", "schools", "or", "the", "replication", "or", "the", "expansion", "of", "existing", "high", "-", "quality", "charter", "schools", "with", "demonstrated", "records", "of", "success", "."], "sentence_id": 91, "word_count": 49}, {"text": "in another example , education officials told us that full - service community schools grants , which support partnerships among schools , school districts , and community - based organizations for coordinated academic , social , and health services can be used to provide those services during extended learning time .", "tokens": ["in", "another", "example", ",", "education", "officials", "told", "us", "that", "full", "-", "service", "community", "schools", "grants", ",", "which", "support", "partnerships", "among", "schools", ",", "school", "districts", ",", "and", "community", "-", "based", "organizations", "for", "coordinated", "academic", ",", "social", ",", "and", "health", "services", "can", "be", "used", "to", "provide", "those", "services", "during", "extended", "learning", "time", "."], "sentence_id": 92, "word_count": 51}, {"text": "representatives from several organizations we interviewed also identified ways that education programs can contribute to extended learning time .", "tokens": ["representatives", "from", "several", "organizations", "we", "interviewed", "also", "identified", "ways", "that", "education", "programs", "can", "contribute", "to", "extended", "learning", "time", "."], "sentence_id": 93, "word_count": 19}, {"text": "for example , a representative from a teachers' union we interviewed told us the union worked with a school that used title i funds to hire a site coordinator who helped the school manage implementation of a longer school day .", "tokens": ["for", "example", ",", "a", "representative", "from", "a", "teachers", "'", "union", "we", "interviewed", "told", "us", "the", "union", "worked", "with", "a", "school", "that", "used", "title", "i", "funds", "to", "hire", "a", "site", "coordinator", "who", "helped", "the", "school", "manage", "implementation", "of", "a", "longer", "school", "day", "."], "sentence_id": 94, "word_count": 42}, {"text": "representatives from extended learning time organizations also told us that title ii funding , which is used for teacher development , was helpful for schools with extended learning time because it allowed them to use the longer day for more professional development .", "tokens": ["representatives", "from", "extended", "learning", "time", "organizations", "also", "told", "us", "that", "title", "ii", "funding", ",", "which", "is", "used", "for", "teacher", "development", ",", "was", "helpful", "for", "schools", "with", "extended", "learning", "time", "because", "it", "allowed", "them", "to", "use", "the", "longer", "day", "for", "more", "professional", "development", "."], "sentence_id": 95, "word_count": 43}, {"text": "a representative from an organization representing school superintendents said school districts may be using title vi funds , which provide assistance to rural schools , to extend learning time .", "tokens": ["a", "representative", "from", "an", "organization", "representing", "school", "superintendents", "said", "school", "districts", "may", "be", "using", "title", "vi", "funds", ",", "which", "provide", "assistance", "to", "rural", "schools", ",", "to", "extend", "learning", "time", "."], "sentence_id": 96, "word_count": 30}, {"text": "education officials cautioned that schools that use federal funds during extended learning time must meet all applicable requirements for those funds , including requirements related to allowable costs and any statutory \u201csupplement not supplant\u201d requirement .", "tokens": ["education", "officials", "cautioned", "that", "schools", "that", "use", "federal", "funds", "during", "extended", "learning", "time", "must", "meet", "all", "applicable", "requirements", "for", "those", "funds", ",", "including", "requirements", "related", "to", "allowable", "costs", "and", "any", "statutory", "\u201c", "supplement", "not", "supplant", "\u201d", "requirement", "."], "sentence_id": 97, "word_count": 38}, {"text": "in general , this requirement precludes a grantee from using federal funds for activities that it would conduct , in the absence of such federal funds , with state or local funds .", "tokens": ["in", "general", ",", "this", "requirement", "precludes", "a", "grantee", "from", "using", "federal", "funds", "for", "activities", "that", "it", "would", "conduct", ",", "in", "the", "absence", "of", "such", "federal", "funds", ",", "with", "state", "or", "local", "funds", "."], "sentence_id": 98, "word_count": 33}, {"text": "on average , we estimate that k - 12 public schools nationwide have a 6.7- hour school day and a 179-day school year , according to our analysis of education's school and staffing survey ( sass ) data for the 2011-2012 school year , the most recent data available ( see fig .", "tokens": ["on", "average", ",", "we", "estimate", "that", "k", "-", "12", "public", "schools", "nationwide", "have", "a", "6.7-", "hour", "school", "day", "and", "a", "179-day", "school", "year", ",", "according", "to", "our", "analysis", "of", "education", "'s", "school", "and", "staffing", "survey", "(", "sass", ")", "data", "for", "the", "2011-2012", "school", "year", ",", "the", "most", "recent", "data", "available", "(", "see", "fig", "."], "sentence_id": 99, "word_count": 54}, {"text": "2 ) .", "tokens": ["2", ")", "."], "sentence_id": 100, "word_count": 3}, {"text": "specifically , an estimated 65 percent of schools have school days that are from 6.5 to 7.5 hours .", "tokens": ["specifically", ",", "an", "estimated", "65", "percent", "of", "schools", "have", "school", "days", "that", "are", "from", "6.5", "to", "7.5", "hours", "."], "sentence_id": 101, "word_count": 19}, {"text": "further , k - 12 public schools that have the most time in school have an estimated average of 1,341 hours in a school year , which is about 137 more hours ( or about four more weeks ) than the estimated national average of 1,204 hours , according to our analysis of education's sass data for the 2011-2012 school year .", "tokens": ["further", ",", "k", "-", "12", "public", "schools", "that", "have", "the", "most", "time", "in", "school", "have", "an", "estimated", "average", "of", "1,341", "hours", "in", "a", "school", "year", ",", "which", "is", "about", "137", "more", "hours", "(", "or", "about", "four", "more", "weeks", ")", "than", "the", "estimated", "national", "average", "of", "1,204", "hours", ",", "according", "to", "our", "analysis", "of", "education", "'s", "sass", "data", "for", "the", "2011-2012", "school", "year", "."], "sentence_id": 102, "word_count": 63}, {"text": "the schools with the most time are going well beyond the hours required per year by most states .", "tokens": ["the", "schools", "with", "the", "most", "time", "are", "going", "well", "beyond", "the", "hours", "required", "per", "year", "by", "most", "states", "."], "sentence_id": 103, "word_count": 19}, {"text": "specifically , a 2015 education commission of the states study found that most states require between 900 and 1,080 hours per year for all grades .", "tokens": ["specifically", ",", "a", "2015", "education", "commission", "of", "the", "states", "study", "found", "that", "most", "states", "require", "between", "900", "and", "1,080", "hours", "per", "year", "for", "all", "grades", "."], "sentence_id": 104, "word_count": 26}, {"text": "the 9,000 schools in the top 10 percent of schools with the most school hours tend to add time by lengthening the school day more so than adding days to the school year .", "tokens": ["the", "9,000", "schools", "in", "the", "top", "10", "percent", "of", "schools", "with", "the", "most", "school", "hours", "tend", "to", "add", "time", "by", "lengthening", "the", "school", "day", "more", "so", "than", "adding", "days", "to", "the", "school", "year", "."], "sentence_id": 105, "word_count": 34}, {"text": "specifically , according to our analysis of sass data , schools in the top 10 percent of schools with the most time typically have a school day that is estimated to be one hour longer than all other schools .", "tokens": ["specifically", ",", "according", "to", "our", "analysis", "of", "sass", "data", ",", "schools", "in", "the", "top", "10", "percent", "of", "schools", "with", "the", "most", "time", "typically", "have", "a", "school", "day", "that", "is", "estimated", "to", "be", "one", "hour", "longer", "than", "all", "other", "schools", "."], "sentence_id": 106, "word_count": 40}, {"text": "further , representatives from the three extended learning time organizations we spoke with told us that most schools extended the day as opposed to adding days in the year .", "tokens": ["further", ",", "representatives", "from", "the", "three", "extended", "learning", "time", "organizations", "we", "spoke", "with", "told", "us", "that", "most", "schools", "extended", "the", "day", "as", "opposed", "to", "adding", "days", "in", "the", "year", "."], "sentence_id": 107, "word_count": 30}, {"text": "one representative told us that the typical schools they partner with have about three additional hours per day and operate monday through friday until 6 p.m .", "tokens": ["one", "representative", "told", "us", "that", "the", "typical", "schools", "they", "partner", "with", "have", "about", "three", "additional", "hours", "per", "day", "and", "operate", "monday", "through", "friday", "until", "6", "p.m", "."], "sentence_id": 108, "word_count": 27}, {"text": "charter schools generally include more hours in a school year than traditional k - 12 public schools ( see fig .", "tokens": ["charter", "schools", "generally", "include", "more", "hours", "in", "a", "school", "year", "than", "traditional", "k", "-", "12", "public", "schools", "(", "see", "fig", "."], "sentence_id": 109, "word_count": 21}, {"text": "3 ) .", "tokens": ["3", ")", "."], "sentence_id": 110, "word_count": 3}, {"text": "specifically , charter schools have an estimated average of 1,285 hours in a school year compared to an average of 1,209 hours for traditional public schools , according to our analysis of education's sass data for the 2011-2012 school year .", "tokens": ["specifically", ",", "charter", "schools", "have", "an", "estimated", "average", "of", "1,285", "hours", "in", "a", "school", "year", "compared", "to", "an", "average", "of", "1,209", "hours", "for", "traditional", "public", "schools", ",", "according", "to", "our", "analysis", "of", "education", "'s", "sass", "data", "for", "the", "2011-2012", "school", "year", "."], "sentence_id": 111, "word_count": 42}, {"text": "further , a larger proportion of charter schools fall into the category of schools with the most time ( 30 percent ) as compared to 9 percent of traditional public schools .", "tokens": ["further", ",", "a", "larger", "proportion", "of", "charter", "schools", "fall", "into", "the", "category", "of", "schools", "with", "the", "most", "time", "(", "30", "percent", ")", "as", "compared", "to", "9", "percent", "of", "traditional", "public", "schools", "."], "sentence_id": 112, "word_count": 32}, {"text": "specifically , of the estimated 2,754 charter schools nationwide , 867 are in the top 10 percent of schools with the most hours .", "tokens": ["specifically", ",", "of", "the", "estimated", "2,754", "charter", "schools", "nationwide", ",", "867", "are", "in", "the", "top", "10", "percent", "of", "schools", "with", "the", "most", "hours", "."], "sentence_id": 113, "word_count": 24}, {"text": "as we have previously reported , charter schools typically operate with more autonomy than traditional public schools .", "tokens": ["as", "we", "have", "previously", "reported", ",", "charter", "schools", "typically", "operate", "with", "more", "autonomy", "than", "traditional", "public", "schools", "."], "sentence_id": 114, "word_count": 18}, {"text": "consequently , charter schools may have fewer barriers than traditional public schools to extending their hours .", "tokens": ["consequently", ",", "charter", "schools", "may", "have", "fewer", "barriers", "than", "traditional", "public", "schools", "to", "extending", "their", "hours", "."], "sentence_id": 115, "word_count": 17}, {"text": "similarly , the time that k - 12 public schools spend on learning differs by region of the country and by school setting ( e.g. , urban or rural ) .", "tokens": ["similarly", ",", "the", "time", "that", "k", "-", "12", "public", "schools", "spend", "on", "learning", "differs", "by", "region", "of", "the", "country", "and", "by", "school", "setting", "(", "e.g", ".", ",", "urban", "or", "rural", ")", "."], "sentence_id": 116, "word_count": 32}, {"text": "schools in the south have an estimated average of 1,253 learning hours per year , in the northeast schools reported an estimated 1,197 hours , in the midwest an estimated 1,192 hours , and the west an estimated 1,146 hours .", "tokens": ["schools", "in", "the", "south", "have", "an", "estimated", "average", "of", "1,253", "learning", "hours", "per", "year", ",", "in", "the", "northeast", "schools", "reported", "an", "estimated", "1,197", "hours", ",", "in", "the", "midwest", "an", "estimated", "1,192", "hours", ",", "and", "the", "west", "an", "estimated", "1,146", "hours", "."], "sentence_id": 117, "word_count": 41}, {"text": "the additional hours means that schools in the south provide , on average , approximately 3 weeks more learning time per year than schools in the west .", "tokens": ["the", "additional", "hours", "means", "that", "schools", "in", "the", "south", "provide", ",", "on", "average", ",", "approximately", "3", "weeks", "more", "learning", "time", "per", "year", "than", "schools", "in", "the", "west", "."], "sentence_id": 118, "word_count": 28}, {"text": "the average number of school hours also differs according to a school's setting .", "tokens": ["the", "average", "number", "of", "school", "hours", "also", "differs", "according", "to", "a", "school", "'s", "setting", "."], "sentence_id": 119, "word_count": 15}, {"text": "an estimated 7 percent of suburban schools were in the top 10 percent of schools with the most learning time , compared to 10 to 12 percent of schools in urban , small town , and rural settings .", "tokens": ["an", "estimated", "7", "percent", "of", "suburban", "schools", "were", "in", "the", "top", "10", "percent", "of", "schools", "with", "the", "most", "learning", "time", ",", "compared", "to", "10", "to", "12", "percent", "of", "schools", "in", "urban", ",", "small", "town", ",", "and", "rural", "settings", "."], "sentence_id": 120, "word_count": 39}, {"text": "conversely , there is little difference in annual school hours by grade level \u2014 such as elementary , middle or high school ( see fig .", "tokens": ["conversely", ",", "there", "is", "little", "difference", "in", "annual", "school", "hours", "by", "grade", "level", "\u2014", "such", "as", "elementary", ",", "middle", "or", "high", "school", "(", "see", "fig", "."], "sentence_id": 121, "word_count": 26}, {"text": "5 ) .", "tokens": ["5", ")", "."], "sentence_id": 122, "word_count": 3}, {"text": "for example , for 90 percent of all public k - 12 schools nationwide , middle schools have the most learning time , with an estimated 1,213 hours in a school year .", "tokens": ["for", "example", ",", "for", "90", "percent", "of", "all", "public", "k", "-", "12", "schools", "nationwide", ",", "middle", "schools", "have", "the", "most", "learning", "time", ",", "with", "an", "estimated", "1,213", "hours", "in", "a", "school", "year", "."], "sentence_id": 123, "word_count": 33}, {"text": "the difference is relatively small , however ; middle schools have an estimated 38 more hours per year than elementary schools and an estimated 36 more hours than for high schools .", "tokens": ["the", "difference", "is", "relatively", "small", ",", "however", ";", "middle", "schools", "have", "an", "estimated", "38", "more", "hours", "per", "year", "than", "elementary", "schools", "and", "an", "estimated", "36", "more", "hours", "than", "for", "high", "schools", "."], "sentence_id": 124, "word_count": 32}, {"text": "for the 10 percent of schools with the most learning time , high schools have the most time , with an estimated 1,428 hours in a school year , but again , the difference is small .", "tokens": ["for", "the", "10", "percent", "of", "schools", "with", "the", "most", "learning", "time", ",", "high", "schools", "have", "the", "most", "time", ",", "with", "an", "estimated", "1,428", "hours", "in", "a", "school", "year", ",", "but", "again", ",", "the", "difference", "is", "small", "."], "sentence_id": 125, "word_count": 37}, {"text": "high schools have an estimated 17 hours more time than elementary schools and an estimated 10 hours more time than middle schools .", "tokens": ["high", "schools", "have", "an", "estimated", "17", "hours", "more", "time", "than", "elementary", "schools", "and", "an", "estimated", "10", "hours", "more", "time", "than", "middle", "schools", "."], "sentence_id": 126, "word_count": 23}, {"text": "one extended learning time provider we spoke with works to extend the learning day for low - income middle school students by providing academic support and project - based apprenticeships .", "tokens": ["one", "extended", "learning", "time", "provider", "we", "spoke", "with", "works", "to", "extend", "the", "learning", "day", "for", "low", "-", "income", "middle", "school", "students", "by", "providing", "academic", "support", "and", "project", "-", "based", "apprenticeships", "."], "sentence_id": 127, "word_count": 31}, {"text": "another extended learning time provider told us its extended learning time model is typically for kindergarten through eighth grades .", "tokens": ["another", "extended", "learning", "time", "provider", "told", "us", "its", "extended", "learning", "time", "model", "is", "typically", "for", "kindergarten", "through", "eighth", "grades", "."], "sentence_id": 128, "word_count": 20}, {"text": "our analysis of sass data for the 2011-2012 school year shows that k - 12 public schools with the most time have a larger proportion of students receiving free or reduced price lunch \u2014 an estimated 61 percent \u2014 than all other schools whose student body population comprises 51 percent of these students ( see fig .", "tokens": ["our", "analysis", "of", "sass", "data", "for", "the", "2011-2012", "school", "year", "shows", "that", "k", "-", "12", "public", "schools", "with", "the", "most", "time", "have", "a", "larger", "proportion", "of", "students", "receiving", "free", "or", "reduced", "price", "lunch", "\u2014", "an", "estimated", "61", "percent", "\u2014", "than", "all", "other", "schools", "whose", "student", "body", "population", "comprises", "51", "percent", "of", "these", "students", "(", "see", "fig", "."], "sentence_id": 129, "word_count": 57}, {"text": "6 ) .", "tokens": ["6", ")", "."], "sentence_id": 130, "word_count": 3}, {"text": "further , public k - 12 schools in the top 10 percent of schools with the most time have a larger proportion of african american and hispanic students \u2014 an estimated 9 percent more african - american students and 7 percent more hispanic students \u2014 than all other schools .", "tokens": ["further", ",", "public", "k", "-", "12", "schools", "in", "the", "top", "10", "percent", "of", "schools", "with", "the", "most", "time", "have", "a", "larger", "proportion", "of", "african", "american", "and", "hispanic", "students", "\u2014", "an", "estimated", "9", "percent", "more", "african", "-", "american", "students", "and", "7", "percent", "more", "hispanic", "students", "\u2014", "than", "all", "other", "schools", "."], "sentence_id": 131, "word_count": 50}, {"text": "one explanation for this could be that , according to our analysis , charter schools serve higher percentages of low income , african american , and hispanic students than traditional public schools .", "tokens": ["one", "explanation", "for", "this", "could", "be", "that", ",", "according", "to", "our", "analysis", ",", "charter", "schools", "serve", "higher", "percentages", "of", "low", "income", ",", "african", "american", ",", "and", "hispanic", "students", "than", "traditional", "public", "schools", "."], "sentence_id": 132, "word_count": 33}, {"text": "african americans account for approximately 27 percent and hispanics for 28 percent of the charter school student body population nationwide compared to 13 and 21 percent in traditional public schools , respectively .", "tokens": ["african", "americans", "account", "for", "approximately", "27", "percent", "and", "hispanics", "for", "28", "percent", "of", "the", "charter", "school", "student", "body", "population", "nationwide", "compared", "to", "13", "and", "21", "percent", "in", "traditional", "public", "schools", ",", "respectively", "."], "sentence_id": 133, "word_count": 33}, {"text": "further , among public schools in the top 10 percent of schools with the most learning time , charters serve a higher percentage of african american and hispanics students compared to traditional public schools .", "tokens": ["further", ",", "among", "public", "schools", "in", "the", "top", "10", "percent", "of", "schools", "with", "the", "most", "learning", "time", ",", "charters", "serve", "a", "higher", "percentage", "of", "african", "american", "and", "hispanics", "students", "compared", "to", "traditional", "public", "schools", "."], "sentence_id": 134, "word_count": 35}, {"text": "specifically , african americans account for approximately 37 percent of students in these schools and hispanics account for 44 percent , compared with 19 and 25 percent in traditional public schools , respectively .", "tokens": ["specifically", ",", "african", "americans", "account", "for", "approximately", "37", "percent", "of", "students", "in", "these", "schools", "and", "hispanics", "account", "for", "44", "percent", ",", "compared", "with", "19", "and", "25", "percent", "in", "traditional", "public", "schools", ",", "respectively", "."], "sentence_id": 135, "word_count": 34}, {"text": "further , one of education's largest grant programs can be used to supplement local initiatives during extended school days or years and targets schools with a high concentration of low - income students .", "tokens": ["further", ",", "one", "of", "education", "'s", "largest", "grant", "programs", "can", "be", "used", "to", "supplement", "local", "initiatives", "during", "extended", "school", "days", "or", "years", "and", "targets", "schools", "with", "a", "high", "concentration", "of", "low", "-", "income", "students", "."], "sentence_id": 136, "word_count": 35}, {"text": "specifically , title i , part a of esea provides funds to school districts and schools that serve high concentrations of low - income students .", "tokens": ["specifically", ",", "title", "i", ",", "part", "a", "of", "esea", "provides", "funds", "to", "school", "districts", "and", "schools", "that", "serve", "high", "concentrations", "of", "low", "-", "income", "students", "."], "sentence_id": 137, "word_count": 26}, {"text": "further , representatives of extended learning time organizations we interviewed told us that the schools they work with tend to extend the school day to improve achievement for students who are low - income and minority who may not have access to the same enrichment activities as their more socioeconomically advantaged peers .", "tokens": ["further", ",", "representatives", "of", "extended", "learning", "time", "organizations", "we", "interviewed", "told", "us", "that", "the", "schools", "they", "work", "with", "tend", "to", "extend", "the", "school", "day", "to", "improve", "achievement", "for", "students", "who", "are", "low", "-", "income", "and", "minority", "who", "may", "not", "have", "access", "to", "the", "same", "enrichment", "activities", "as", "their", "more", "socioeconomically", "advantaged", "peers", "."], "sentence_id": 138, "word_count": 53}, {"text": "one representative from an extended learning time organization told us that its programs seek to close gaps in opportunity and educational achievement for disadvantaged communities .", "tokens": ["one", "representative", "from", "an", "extended", "learning", "time", "organization", "told", "us", "that", "its", "programs", "seek", "to", "close", "gaps", "in", "opportunity", "and", "educational", "achievement", "for", "disadvantaged", "communities", "."], "sentence_id": 139, "word_count": 26}, {"text": "public k - 12 schools with the most hours in a school year use this additional time for different purposes , including more instruction in math and literacy , and more time for the arts and physical education .", "tokens": ["public", "k", "-", "12", "schools", "with", "the", "most", "hours", "in", "a", "school", "year", "use", "this", "additional", "time", "for", "different", "purposes", ",", "including", "more", "instruction", "in", "math", "and", "literacy", ",", "and", "more", "time", "for", "the", "arts", "and", "physical", "education", "."], "sentence_id": 140, "word_count": 39}, {"text": "for example , during the 2011-2012 school year , eighth - grade students in schools with the most time ( the top 10 percent ) are estimated to have spent an additional 1.3 hours per week , on average , in english language arts , math , and science instruction compared to eighth - graders in all other schools .", "tokens": ["for", "example", ",", "during", "the", "2011-2012", "school", "year", ",", "eighth", "-", "grade", "students", "in", "schools", "with", "the", "most", "time", "(", "the", "top", "10", "percent", ")", "are", "estimated", "to", "have", "spent", "an", "additional", "1.3", "hours", "per", "week", ",", "on", "average", ",", "in", "english", "language", "arts", ",", "math", ",", "and", "science", "instruction", "compared", "to", "eighth", "-", "graders", "in", "all", "other", "schools", "."], "sentence_id": 141, "word_count": 60}, {"text": "further , third - grade students in schools with the most time spent an estimated additional 48 minutes per week , on average , in music , art , and physical education classes than third - graders in all other schools , according to our analysis of sass data .", "tokens": ["further", ",", "third", "-", "grade", "students", "in", "schools", "with", "the", "most", "time", "spent", "an", "estimated", "additional", "48", "minutes", "per", "week", ",", "on", "average", ",", "in", "music", ",", "art", ",", "and", "physical", "education", "classes", "than", "third", "-", "graders", "in", "all", "other", "schools", ",", "according", "to", "our", "analysis", "of", "sass", "data", "."], "sentence_id": 142, "word_count": 50}, {"text": "representatives from the three extended learning organizations we spoke with told us that their programs provide students more time for instruction in academic subjects and for enrichment activities , such as a debate club and project - based learning activities in science .", "tokens": ["representatives", "from", "the", "three", "extended", "learning", "organizations", "we", "spoke", "with", "told", "us", "that", "their", "programs", "provide", "students", "more", "time", "for", "instruction", "in", "academic", "subjects", "and", "for", "enrichment", "activities", ",", "such", "as", "a", "debate", "club", "and", "project", "-", "based", "learning", "activities", "in", "science", "."], "sentence_id": 143, "word_count": 43}, {"text": "teachers in the schools with the most time spend more time providing instruction to students as compared to all other schools .", "tokens": ["teachers", "in", "the", "schools", "with", "the", "most", "time", "spend", "more", "time", "providing", "instruction", "to", "students", "as", "compared", "to", "all", "other", "schools", "."], "sentence_id": 144, "word_count": 22}, {"text": "specifically , teachers in schools with the most time ( the top 10 percent ) teach an estimated 1.3 more hours per week compared to all other schools , with a weekly total of 31.2 hours compared to 29.8 hours .", "tokens": ["specifically", ",", "teachers", "in", "schools", "with", "the", "most", "time", "(", "the", "top", "10", "percent", ")", "teach", "an", "estimated", "1.3", "more", "hours", "per", "week", "compared", "to", "all", "other", "schools", ",", "with", "a", "weekly", "total", "of", "31.2", "hours", "compared", "to", "29.8", "hours", "."], "sentence_id": 145, "word_count": 41}, {"text": "on the other hand , there was no significant difference in the hours spent in a school year on professional development between schools with the most time and all other schools .", "tokens": ["on", "the", "other", "hand", ",", "there", "was", "no", "significant", "difference", "in", "the", "hours", "spent", "in", "a", "school", "year", "on", "professional", "development", "between", "schools", "with", "the", "most", "time", "and", "all", "other", "schools", "."], "sentence_id": 146, "word_count": 32}, {"text": "further , according to a representative from one extended learning time organization with whom we spoke , schools often partner with external participants or providers of after - school programs to provide academic instruction or enrichment activities during the school day .", "tokens": ["further", ",", "according", "to", "a", "representative", "from", "one", "extended", "learning", "time", "organization", "with", "whom", "we", "spoke", ",", "schools", "often", "partner", "with", "external", "participants", "or", "providers", "of", "after", "-", "school", "programs", "to", "provide", "academic", "instruction", "or", "enrichment", "activities", "during", "the", "school", "day", "."], "sentence_id": 147, "word_count": 42}, {"text": "we are not making recommendations in this report .", "tokens": ["we", "are", "not", "making", "recommendations", "in", "this", "report", "."], "sentence_id": 148, "word_count": 9}, {"text": "we provided a draft of this report to the department of education for comment .", "tokens": ["we", "provided", "a", "draft", "of", "this", "report", "to", "the", "department", "of", "education", "for", "comment", "."], "sentence_id": 149, "word_count": 15}, {"text": "education provided technical comments , which we incorporated as appropriate .", "tokens": ["education", "provided", "technical", "comments", ",", "which", "we", "incorporated", "as", "appropriate", "."], "sentence_id": 150, "word_count": 11}, {"text": "we are sending copies of this report to the appropriate congressional committees , the secretary of education , and other interested parties .", "tokens": ["we", "are", "sending", "copies", "of", "this", "report", "to", "the", "appropriate", "congressional", "committees", ",", "the", "secretary", "of", "education", ",", "and", "other", "interested", "parties", "."], "sentence_id": 151, "word_count": 23}, {"text": "in addition , the report will be available at no charge on gao's web site at http: / / www.gao.gov .", "tokens": ["in", "addition", ",", "the", "report", "will", "be", "available", "at", "no", "charge", "on", "gao", "'s", "web", "site", "at", "http", ":", "/", "/", "www.gao.gov", "."], "sentence_id": 152, "word_count": 23}, {"text": "if you or your staff should have any questions about this report , please contact me at ( 617 ) 788-0580 or nowickij@gao.gov .", "tokens": ["if", "you", "or", "your", "staff", "should", "have", "any", "questions", "about", "this", "report", ",", "please", "contact", "me", "at", "(", "617", ")", "788-0580", "or", "nowickij", "@", "gao.gov", "."], "sentence_id": 153, "word_count": 26}, {"text": "contact points for our offices of congressional relations and public affairs may be found on the last page of this report .", "tokens": ["contact", "points", "for", "our", "offices", "of", "congressional", "relations", "and", "public", "affairs", "may", "be", "found", "on", "the", "last", "page", "of", "this", "report", "."], "sentence_id": 154, "word_count": 22}, {"text": "gao staff who made key contributions to this report are listed in appendix i .", "tokens": ["gao", "staff", "who", "made", "key", "contributions", "to", "this", "report", "are", "listed", "in", "appendix", "i", "."], "sentence_id": 155, "word_count": 15}, {"text": "in addition to the contact named above , elizabeth sirois ( assistant director ) , sheranda campbell ( analyst - in - charge ) , and lucas alvarez made significant contributions to this report .", "tokens": ["in", "addition", "to", "the", "contact", "named", "above", ",", "elizabeth", "sirois", "(", "assistant", "director", ")", ",", "sheranda", "campbell", "(", "analyst", "-", "in", "-", "charge", ")", ",", "and", "lucas", "alvarez", "made", "significant", "contributions", "to", "this", "report", "."], "sentence_id": 156, "word_count": 35}, {"text": "assistance , expertise , and guidance were provided by susan aschoff , james rebbe , kirsten lauber , john mingus , carl barden , and james bennett .", "tokens": ["assistance", ",", "expertise", ",", "and", "guidance", "were", "provided", "by", "susan", "aschoff", ",", "james", "rebbe", ",", "kirsten", "lauber", ",", "john", "mingus", ",", "carl", "barden", ",", "and", "james", "bennett", "."], "sentence_id": 157, "word_count": 28}], "section_names": ["letter", "background", "school improvement grants program", "21st century program", "k-12 public school funding", "education supports extended learning time primarily through the school improvement grants program", "education promoted extended learning time in k-12 public schools with nearly 1,800 school improvement grants", "very few grantees used 21st century grants to support extended learning time", "schools may use other education funding during extended learning time", "schools with the most time in school share certain characteristics and use the additional time for different purposes", "average length of k-12 public school day was just under 7 hours, and those with the most time add hours to the day, not days to the school year", "time varies by school type and school location, but little by grade level", "schools with the most hours in a school year serve larger proportions of low-income and african american and hispanic students", "schools with the most hours spend more time on instruction", "agency comments", "appendix i: gao contact and staff acknowledgments", "gao contact", "staff acknowledgments"], "section_lengths": [39, 0, 8, 7, 5, 0, 13, 14, 12, 0, 10, 20, 11, 8, 8, 0, 0, 2]}